README.md
setup.cfg
setup.py
httpbase/__init__.py
httpbase/client.py
httpbase/constants.py
httpbase/exceptions.py
httpbase/fields.py
httpbase/resources.py
httpbase/routes.py
httpbase.egg-info/PKG-INFO
httpbase.egg-info/SOURCES.txt
httpbase.egg-info/dependency_links.txt
httpbase.egg-info/not-zip-safe
httpbase.egg-info/requires.txt
httpbase.egg-info/top_level.txt
tests/__init__.py
tests/test_client.py
tests/test_http_codes.py
tests/test_routes.py
tests/test_fields/__init__.py
tests/test_fields/test_bool_field.py
tests/test_fields/test_date_field.py
tests/test_fields/test_epoch_field.py
tests/test_fields/test_int_field.py
tests/test_fields/test_list_field.py
tests/test_fields/test_map_field.py
tests/test_fields/test_resource_field.py
tests/test_fields/test_str_field.py
tests/test_resources/__init__.py
tests/test_resources/_test_classes.py
tests/test_resources/test_accessors.py
tests/test_resources/test_resources.py