Metadata-Version: 1.0
Name: httpbase
Version: 0.6.1
Summary: Library for quickly making those simple HTTP clients we all end up writing all the time
Home-page: UNKNOWN
Author: Ian Auld
Author-email: imauld@gmail.com
License: UNKNOWN
Platform: UNKNOWN
